maykin_common/__init__.py
maykin_common/apps.py
maykin_common/checks.py
maykin_common/cli.py
maykin_common/config.py
maykin_common/context_processors.py
maykin_common/django_two_factor_auth.py
maykin_common/migration_operations.py
maykin_common/otel.py
maykin_common/pdf.py
maykin_common/py.typed
maykin_common/settings.py
maykin_common/throttling.py
maykin_common/vcr.py
maykin_common/views.py
maykin_common/accounts/__init__.py
maykin_common/accounts/views.py
maykin_common/api_reference/__init__.py
maykin_common/api_reference/views.py
maykin_common/drf_spectacular/__init__.py
maykin_common/drf_spectacular/hooks.py
maykin_common/health_checks/__init__.py
maykin_common/health_checks/defaults.py
maykin_common/health_checks/urls.py
maykin_common/health_checks/celery/__init__.py
maykin_common/health_checks/celery/apps.py
maykin_common/health_checks/celery/probes.py
maykin_common/locale/nl/LC_MESSAGES/django.mo
maykin_common/locale/nl/LC_MESSAGES/django.po
maykin_common/management/__init__.py
maykin_common/management/commands/__init__.py
maykin_common/management/commands/clear_cache.py
maykin_common/static/maykin_common/css/api.css
maykin_common/static/maykin_common/css/version.css
maykin_common/static/maykin_common/ico/favicon-32x32.png
maykin_common/static/maykin_common/ico/favicon-96x96.png
maykin_common/static/maykin_common/ico/favicon.png
maykin_common/static/maykin_common/ico/favicon.svg
maykin_common/static/maykin_common/js/nav-tabs.js
maykin_common/templates/500.html
maykin_common/templates/maykin_common/api/index_base.html
maykin_common/templates/maykin_common/api/index_component.html
maykin_common/templates/maykin_common/api/includes/footer.html
maykin_common/templates/maykin_common/includes/version_info.html
maykin_common/templatetags/__init__.py
maykin_common/templatetags/maykin_common.py
maykin_common/tests/__init__.py
maykin_common/tests/otel.py
maykin_common-0.14.0.dist-info/licenses/LICENSE
maykin_common-0.14.0.dist-info/METADATA
maykin_common-0.14.0.dist-info/WHEEL
maykin_common-0.14.0.dist-info/entry_points.txt
maykin_common-0.14.0.dist-info/top_level.txt
maykin_common-0.14.0.dist-info/RECORD
