Metadata-Version: 2.4
Name: maykin-common
Version: 0.14.0
Summary: Re-usable utilities for Maykin Django projects, centrally maintained instead of in default-project.
Author-email: Maykin Media <support@maykinmedia.nl>
License-Expression: MIT
Project-URL: Homepage, https://github.com/maykinmedia/django-common
Project-URL: Documentation, http://maykin-django-common.readthedocs.io/en/latest/
Project-URL: Bug Tracker, https://github.com/maykinmedia/django-common/issues
Project-URL: Source Code, https://github.com/maykinmedia/django-common
Keywords: django,maykin,boilerplate
Classifier: Development Status :: 3 - Alpha
Classifier: Framework :: Django
Classifier: Framework :: Django :: 4.2
Classifier: Framework :: Django :: 5.2
Classifier: Intended Audience :: Developers
Classifier: Operating System :: Unix
Classifier: Operating System :: MacOS
Classifier: Operating System :: Microsoft :: Windows
Classifier: Programming Language :: Python :: 3.12
Classifier: Programming Language :: Python :: 3.13
Classifier: Topic :: Software Development :: Libraries :: Python Modules
Requires-Python: >=3.12
License-File: LICENSE
Requires-Dist: django>=4.2
Requires-Dist: python-decouple
Provides-Extra: tests
Requires-Dist: psycopg; extra == "tests"
Requires-Dist: django-test-migrations; extra == "tests"
Requires-Dist: pytest; extra == "tests"
Requires-Dist: pytest-django; extra == "tests"
Requires-Dist: pytest-cov; extra == "tests"
Requires-Dist: pytest-playwright; extra == "tests"
Requires-Dist: tox; extra == "tests"
Requires-Dist: ruff; extra == "tests"
Requires-Dist: pyright; extra == "tests"
Requires-Dist: django-stubs; extra == "tests"
Requires-Dist: decouple-types; extra == "tests"
Requires-Dist: celery; extra == "tests"
Requires-Dist: redis; extra == "tests"
Provides-Extra: docs
Requires-Dist: sphinx; extra == "docs"
Requires-Dist: sphinx-rtd-theme; extra == "docs"
Provides-Extra: release
Requires-Dist: bump-my-version; extra == "release"
Provides-Extra: cli
Requires-Dist: requests; extra == "cli"
Requires-Dist: typer; extra == "cli"
Provides-Extra: pdf
Requires-Dist: weasyprint; extra == "pdf"
Provides-Extra: mfa
Requires-Dist: django-admin-index; extra == "mfa"
Requires-Dist: maykin-2fa; extra == "mfa"
Provides-Extra: axes
Requires-Dist: django-axes; extra == "axes"
Provides-Extra: vcr
Requires-Dist: vcrpy; extra == "vcr"
Requires-Dist: requests; extra == "vcr"
Requires-Dist: types-requests; extra == "vcr"
Provides-Extra: otel
Requires-Dist: opentelemetry-api; extra == "otel"
Requires-Dist: opentelemetry-exporter-otlp; extra == "otel"
Requires-Dist: opentelemetry-instrumentation-django; extra == "otel"
Requires-Dist: opentelemetry-resource-detector-containerid; extra == "otel"
Requires-Dist: opentelemetry-sdk; extra == "otel"
Provides-Extra: health-checks
Requires-Dist: django-health-check>=3.20; extra == "health-checks"
Dynamic: license-file
